{"cameraMode":{"drawMode":0,"name":"Shaded","section":"Shading Mode"},"sceneLighting":true,"audioPlay":false,"sceneViewState":{"m_AlwaysRefresh":false,"showFog":true,"showSkybox":true,"showFlares":true,"showImageEffects":true,"showParticleSystems":true,"showVisualEffectGraphs":true,"m_FxEnabled":true},"in2DMode":false,"pivot":{"x":-32.167049407958987,"y":1.345482349395752,"z":-3.0180931091308595},"rotation":{"x":0.025804240256547929,"y":0.9706719517707825,"z":-0.12178231030702591,"w":0.20567530393600465},"size":9.979750633239746,"orthographic":false}